noWord/__init__.py
noWord/nw_proc.py
noWord/common/DefaultDecoration.py
noWord/common/DefaultStyles.py
noWord/common/DefaultTransformation.py
noWord/common/NWDocument.py
noWord/common/NWGenerator.py
noWord/common/NWProcContext.py
noWord/common/NWTestCase.py
noWord/common/PluginInterface.py
noWord/common/PluginManager.py
noWord/common/__init__.py
noWord/common/utils_di.py
noWord/common/utils_fs.py
noWord/common/utils_rp.py
noWord/common/assets/FontAwesome.ttf
noWord/common/assets/Arimo/Arimo-Bold.ttf
noWord/common/assets/Arimo/Arimo-BoldItalic.ttf
noWord/common/assets/Arimo/Arimo-Italic.ttf
noWord/common/assets/Arimo/Arimo-Regular.ttf
noWord/common/assets/Arimo/LICENSE.txt
noWord/common/flowables/HLine.py
noWord/common/flowables/Measure.py
noWord/common/flowables/Metadata.py
noWord/common/flowables/PDFImage.py
noWord/common/flowables/ProgressBar.py
noWord/common/flowables/Sticker.py
noWord/common/flowables/VerticalText.py
noWord/common/flowables/__init__.py
noWord/plugins/__init__.py
noWord/plugins/AnchorBlock/AnchorBlock.py
noWord/plugins/AnchorBlock/__init__.py
noWord/plugins/AnchorBlock/manual.md
noWord/plugins/ChapterBlock/ChapterBlock.py
noWord/plugins/ChapterBlock/TOCBuilder.py
noWord/plugins/ChapterBlock/__init__.py
noWord/plugins/ChapterBlock/manual.md
noWord/plugins/ChartBlock/ChartBlock.py
noWord/plugins/ChartBlock/__init__.py
noWord/plugins/ChartBlock/manual.md
noWord/plugins/DecorationBlock/DecorationBlock.py
noWord/plugins/DecorationBlock/__init__.py
noWord/plugins/DecorationBlock/manual.md
noWord/plugins/ForeachBlock/ForeachBlock.py
noWord/plugins/ForeachBlock/__init__.py
noWord/plugins/ForeachBlock/manual.md
noWord/plugins/ImageBlock/ImageBlock.py
noWord/plugins/ImageBlock/__init__.py
noWord/plugins/ImageBlock/manual.md
noWord/plugins/LineBlock/LineBlock.py
noWord/plugins/LineBlock/__init__.py
noWord/plugins/LineBlock/manual.md
noWord/plugins/ListBlock/ListBlock.py
noWord/plugins/ListBlock/__init__.py
noWord/plugins/ListBlock/manual.md
noword-1.1.0.dist-info/METADATA
noword-1.1.0.dist-info/WHEEL
noword-1.1.0.dist-info/entry_points.txt
noword-1.1.0.dist-info/licenses/LICENSE
noword-1.1.0.dist-info/RECORD
