Metadata-Version: 2.4
Name: noWord
Version: 1.1.0
Summary: non-WYSIWYG document generator
Project-URL: Homepage, https://github.com/mmuellersk/noWord
Project-URL: Issues, https://github.com/mmuellersk/noWord/issues
Author-email: Matthias Müller <mmueller.sk@gmail.com>
License-Expression: GPL-3.0-only
License-File: LICENSE
Classifier: Operating System :: OS Independent
Classifier: Programming Language :: Python :: 3
Requires-Python: >=3.9
Requires-Dist: pdfrw==0.4
Requires-Dist: pyyaml==6.0.2
Requires-Dist: reportlab==4.4.2
Requires-Dist: xmltodict==0.12.0
